mldev/__init__.py
mldev/__version__.py
ml_dev-0.1.dev0.dist-info/LICENSE
ml_dev-0.1.dev0.dist-info/METADATA
ml_dev-0.1.dev0.dist-info/WHEEL
ml_dev-0.1.dev0.dist-info/top_level.txt
ml_dev-0.1.dev0.dist-info/RECORD
